demoviz/__init__.py
demoviz/_version.py
demoviz/core.py
demoviz/matplotlib_integration.py
demoviz/seaborn_integration.py
demoviz/icons/Person_icon_BLACK-01.svg
demoviz/icons/Woman_(958542)_-_The_Noun_Project.svg
demoviz-0.1.0.dist-info/METADATA
demoviz-0.1.0.dist-info/WHEEL
demoviz-0.1.0.dist-info/top_level.txt
demoviz-0.1.0.dist-info/RECORD
