Metadata-Version: 2.4
Name: demoviz
Version: 0.1.0
Summary: Demographic data visualization with human icons for matplotlib
Author-email: Matthias Flotho <matthias.flotho@ccb.uni-saarland.de>
License: MIT
Project-URL: Homepage, https://github.com/maflot/demoviz
Project-URL: Repository, https://github.com/maflot/demoviz.git
Project-URL: Issues, https://github.com/maflot/demoviz/issues
Project-URL: Documentation, https://demoviz.readthedocs.io
Keywords: matplotlib,visualization,demographics,scatter,icons,human
Classifier: Development Status :: 3 - Alpha
Classifier: Intended Audience :: Science/Research
Classifier: Intended Audience :: Healthcare Industry
Classifier: License :: OSI Approved :: MIT License
Classifier: Programming Language :: Python :: 3
Classifier: Programming Language :: Python :: 3.8
Classifier: Programming Language :: Python :: 3.9
Classifier: Programming Language :: Python :: 3.10
Classifier: Programming Language :: Python :: 3.11
Classifier: Programming Language :: Python :: 3.12
Classifier: Topic :: Scientific/Engineering :: Visualization
Classifier: Topic :: Scientific/Engineering :: Medical Science Apps.
Requires-Python: >=3.8
Requires-Dist: matplotlib>=3.5.0
Requires-Dist: numpy>=1.20.0
Requires-Dist: Pillow>=8.0.0
Provides-Extra: svg
Requires-Dist: cairosvg>=2.5.0; extra == "svg"
Provides-Extra: seaborn
Requires-Dist: seaborn>=0.11.0; extra == "seaborn"
Provides-Extra: pandas
Requires-Dist: pandas>=1.3.0; extra == "pandas"
Provides-Extra: all
Requires-Dist: cairosvg>=2.5.0; extra == "all"
Requires-Dist: seaborn>=0.11.0; extra == "all"
Requires-Dist: pandas>=1.3.0; extra == "all"
Provides-Extra: dev
Requires-Dist: pytest>=6.0; extra == "dev"
Requires-Dist: pytest-cov; extra == "dev"
Requires-Dist: black; extra == "dev"
Requires-Dist: flake8; extra == "dev"
Requires-Dist: build; extra == "dev"
Requires-Dist: twine; extra == "dev"
Requires-Dist: jupyter; extra == "dev"
Requires-Dist: matplotlib>=3.5.0; extra == "dev"
Requires-Dist: cairosvg>=2.5.0; extra == "dev"
Requires-Dist: seaborn>=0.11.0; extra == "dev"
Requires-Dist: pandas>=1.3.0; extra == "dev"
